{
    "id": "299544e0-0a52-4859-86bc-eb7647ce5d86",
    "url": "https://ll.thespacedevs.com/2.2.0/launch/299544e0-0a52-4859-86bc-eb7647ce5d86/",
    "slug": "x-15-flight-190",
    "name": "X-15 | Flight 190",
    "status": {
        "id": 3,
        "name": "Launch Successful",
        "abbrev": "Success",
        "description": "The launch vehicle successfully inserted its payload(s) into the target orbit(s)."
    },
    "last_updated": "2023-06-14T08:59:12Z",
    "net": "1967-10-17T17:40:00Z",
    "window_end": "1967-10-17T17:50:00Z",
    "window_start": "1967-10-17T17:40:00Z",
    "net_precision": null,
    "probability": null,
    "weather_concerns": null,
    "holdreason": "",
    "failreason": "",
    "hashtag": null,
    "launch_service_provider": {
        "id": 161,
        "url": "https://ll.thespacedevs.com/2.2.0/agencies/161/",
        "name": "United States Air Force",
        "type": "Government"
    },
    "rocket": {
        "id": 2990,
        "configuration": {
            "id": 209,
            "url": "https://ll.thespacedevs.com/2.2.0/config/launcher/209/",
            "name": "North American X-15",
            "family": "",
            "full_name": "North American X-15",
            "variant": ""
        }
    },
    "mission": {
        "id": 1415,
        "name": "Flight 190",
        "description": "Flight 190 of the North American X-15 was a test flight conducted by NASA and the US Air Force in 1967. Piloted by William J. Knight  it reached an altitude of 85.5 km.",
        "launch_designator": null,
        "type": "Test Flight",
        "orbit": {
            "id": 15,
            "name": "Suborbital",
            "abbrev": "Sub"
        },
        "agencies": [],
        "info_urls": [],
        "vid_urls": []
    },
    "pad": {
        "id": 112,
        "url": "https://ll.thespacedevs.com/2.2.0/pad/112/",
        "agency_id": null,
        "name": "Edwards Air Force Base",
        "description": null,
        "info_url": null,
        "wiki_url": "https://en.wikipedia.org/wiki/Edwards_Air_Force_Base",
        "map_url": "https://www.google.com/maps?q=34.905556,-117.883611",
        "latitude": "34.905556",
        "longitude": "-117.883611",
        "location": {
            "id": 144,
            "url": "https://ll.thespacedevs.com/2.2.0/location/144/",
            "name": "Air launch to Suborbital flight",
            "country_code": "???",
            "description": "",
            "map_image": "https://thespacedevs-prod.nyc3.digitaloceanspaces.com/media/map_images/location_144_20200803142439.jpg",
            "timezone_name": "",
            "total_launch_count": 86,
            "total_landing_count": 0
        },
        "country_code": "USA",
        "map_image": "https://thespacedevs-prod.nyc3.digitaloceanspaces.com/media/map_images/pad_112_20200803143214.jpg",
        "total_launch_count": 13,
        "orbital_launch_attempt_count": 0
    },
    "webcast_live": false,
    "image": "https://thespacedevs-prod.nyc3.digitaloceanspaces.com/media/images/north_american__image_20210813101104.png",
    "infographic": null,
    "program": [
        {
            "id": 20,
            "url": "https://ll.thespacedevs.com/2.2.0/program/20/",
            "name": "X-15",
            "description": "Experimental hypersonic rocket-powered aircraft.",
            "agencies": [
                {
                    "id": 44,
                    "url": "https://ll.thespacedevs.com/2.2.0/agencies/44/",
                    "name": "National Aeronautics and Space Administration",
                    "type": "Government"
                },
                {
                    "id": 161,
                    "url": "https://ll.thespacedevs.com/2.2.0/agencies/161/",
                    "name": "United States Air Force",
                    "type": "Government"
                }
            ],
            "image_url": "https://thespacedevs-prod.nyc3.digitaloceanspaces.com/media/images/x-15_program_20210809102752.jpeg",
            "start_date": "1959-03-10T00:00:00Z",
            "end_date": "1968-12-12T00:00:00Z",
            "info_url": null,
            "wiki_url": "https://en.wikipedia.org/wiki/North_American_X-15",
            "mission_patches": [],
            "type": {
                "id": 2,
                "name": "Human Spaceflight"
            }
        }
    ],
    "orbital_launch_attempt_count": null,
    "location_launch_attempt_count": 17,
    "pad_launch_attempt_count": 11,
    "agency_launch_attempt_count": 422,
    "orbital_launch_attempt_count_year": 0,
    "location_launch_attempt_count_year": 1,
    "pad_launch_attempt_count_year": 1,
    "agency_launch_attempt_count_year": 50,
    "type": "normal"
}