{
    "id": "b992f5a6-9a9f-4af1-9ebd-7ee2dd6047c8",
    "url": "https://ll.thespacedevs.com/2.2.0/launch/b992f5a6-9a9f-4af1-9ebd-7ee2dd6047c8/",
    "slug": "titan-iiie-voyager-1",
    "name": "Titan IIIE | Voyager 1",
    "status": {
        "id": 3,
        "name": "Launch Successful",
        "abbrev": "Success",
        "description": "The launch vehicle successfully inserted its payload(s) into the target orbit(s)."
    },
    "last_updated": "2024-06-15T14:38:29Z",
    "net": "1977-09-05T12:56:01Z",
    "window_end": "1977-09-05T12:56:01Z",
    "window_start": "1977-09-05T12:56:01Z",
    "net_precision": {
        "id": 0,
        "name": "Second",
        "abbrev": "SEC",
        "description": "The T-0 is accurate to the second."
    },
    "probability": null,
    "weather_concerns": null,
    "holdreason": "",
    "failreason": "",
    "hashtag": null,
    "launch_service_provider": {
        "id": 82,
        "url": "https://ll.thespacedevs.com/2.2.0/agencies/82/",
        "name": "Lockheed Martin",
        "type": "Commercial"
    },
    "rocket": {
        "id": 261,
        "configuration": {
            "id": 148,
            "url": "https://ll.thespacedevs.com/2.2.0/config/launcher/148/",
            "name": "Titan III",
            "family": "Titan",
            "full_name": "Titan IIIE",
            "variant": "E"
        }
    },
    "mission": {
        "id": 508,
        "name": "Voyager 1",
        "description": "Voyager 1 is a space probe launched by NASA on September 5, 1977. Part of the Voyager program to study the outer Solar System, Voyager 1 launched 16 days after its twin, Voyager 2.",
        "launch_designator": null,
        "type": "Robotic Exploration",
        "orbit": {
            "id": 14,
            "name": "Solar Escape Trajectory",
            "abbrev": "Solar Esc."
        },
        "agencies": [],
        "info_urls": [],
        "vid_urls": []
    },
    "pad": {
        "id": 29,
        "url": "https://ll.thespacedevs.com/2.2.0/pad/29/",
        "agency_id": null,
        "name": "Space Launch Complex 41",
        "description": "",
        "info_url": null,
        "wiki_url": "https://en.wikipedia.org/wiki/Cape_Canaveral_Air_Force_Station_Space_Launch_Complex_41",
        "map_url": "https://www.google.com/maps?q=28.58341025,-80.58303644",
        "latitude": "28.58341025",
        "longitude": "-80.58303644",
        "location": {
            "id": 12,
            "url": "https://ll.thespacedevs.com/2.2.0/location/12/",
            "name": "Cape Canaveral SFS, FL, USA",
            "country_code": "USA",
            "description": "Cape Canaveral Space Force Station (CCSFS) is an installation of the United States Space Force's Space Launch Delta 45, located on Cape Canaveral in Brevard County, Florida.",
            "map_image": "https://thespacedevs-prod.nyc3.digitaloceanspaces.com/media/map_images/location_12_20200803142519.jpg",
            "timezone_name": "America/New_York",
            "total_launch_count": 989,
            "total_landing_count": 59
        },
        "country_code": "USA",
        "map_image": "https://thespacedevs-prod.nyc3.digitaloceanspaces.com/media/map_images/pad_29_20200803143528.jpg",
        "total_launch_count": 114,
        "orbital_launch_attempt_count": 114
    },
    "webcast_live": false,
    "image": "https://thespacedevs-prod.nyc3.digitaloceanspaces.com/media/images/titan2520iii_image_20190222030055.jpeg",
    "infographic": null,
    "program": [
        {
            "id": 36,
            "url": "https://ll.thespacedevs.com/2.2.0/program/36/",
            "name": "NASA Large Strategic Science Missions",
            "description": "NASA's large strategic science missions or large strategic missions, formerly known as Flagship missions or Flagship-class missions, are the costliest and most capable NASA science spacecraft. Flagship missions exist within all four divisions of NASA's Science Mission Directorate (SMD): the astrophysics, Earth science, heliophysics and planetary science divisions.",
            "agencies": [
                {
                    "id": 44,
                    "url": "https://ll.thespacedevs.com/2.2.0/agencies/44/",
                    "name": "National Aeronautics and Space Administration",
                    "type": "Government"
                }
            ],
            "image_url": "https://thespacedevs-prod.nyc3.digitaloceanspaces.com/media/images/nasa2520large_program_20240205122003.jpeg",
            "start_date": "1975-08-22T00:00:00Z",
            "end_date": null,
            "info_url": null,
            "wiki_url": "https://en.wikipedia.org/wiki/Large_strategic_science_missions",
            "mission_patches": [],
            "type": {
                "id": 5,
                "name": "Exploration"
            }
        }
    ],
    "orbital_launch_attempt_count": 2002,
    "location_launch_attempt_count": 330,
    "pad_launch_attempt_count": 17,
    "agency_launch_attempt_count": 7,
    "orbital_launch_attempt_count_year": 87,
    "location_launch_attempt_count_year": 13,
    "pad_launch_attempt_count_year": 2,
    "agency_launch_attempt_count_year": 2,
    "type": "normal"
}