{
    "id": "20d9789c-dfdf-46b5-a964-de5f031615a5",
    "url": "https://ll.thespacedevs.com/2.2.0/launch/20d9789c-dfdf-46b5-a964-de5f031615a5/",
    "slug": "launcherone-launch-demo-2",
    "name": "LauncherOne | Launch Demo 2",
    "status": {
        "id": 3,
        "name": "Launch Successful",
        "abbrev": "Success",
        "description": "The launch vehicle successfully inserted its payload(s) into the target orbit(s)."
    },
    "last_updated": "2023-06-14T03:54:38Z",
    "net": "2021-01-17T19:38:51Z",
    "window_end": "2021-01-17T22:00:00Z",
    "window_start": "2021-01-17T18:00:00Z",
    "net_precision": null,
    "probability": -1,
    "weather_concerns": null,
    "holdreason": "",
    "failreason": "",
    "hashtag": null,
    "launch_service_provider": {
        "id": 199,
        "url": "https://ll.thespacedevs.com/2.2.0/agencies/199/",
        "name": "Virgin Orbit",
        "type": "Commercial"
    },
    "rocket": {
        "id": 2736,
        "configuration": {
            "id": 141,
            "url": "https://ll.thespacedevs.com/2.2.0/config/launcher/141/",
            "name": "LauncherOne",
            "family": "",
            "full_name": "LauncherOne",
            "variant": "One"
        }
    },
    "mission": {
        "id": 496,
        "name": "Launch Demo 2 (VCLS ELaNa XX)",
        "description": "This is Virgin Orbit's second attempt to launch the LauncherOne rocket. It also carries cubesats which were contracted by NASA through Venture Class Launch Services contract.",
        "launch_designator": null,
        "type": "Dedicated Rideshare",
        "orbit": {
            "id": 13,
            "name": "Polar Orbit",
            "abbrev": "PO"
        },
        "agencies": [],
        "info_urls": [],
        "vid_urls": []
    },
    "pad": {
        "id": 53,
        "url": "https://ll.thespacedevs.com/2.2.0/pad/53/",
        "agency_id": null,
        "name": "Mojave Air and Space Port",
        "description": null,
        "info_url": null,
        "wiki_url": "https://en.wikipedia.org/wiki/Mojave_Air_and_Space_Port",
        "map_url": "https://www.google.com/maps?q=35.059444,-118.151667",
        "latitude": "35.059444",
        "longitude": "-118.151667",
        "location": {
            "id": 20,
            "url": "https://ll.thespacedevs.com/2.2.0/location/20/",
            "name": "Air launch to orbit",
            "country_code": "???",
            "description": "",
            "map_image": "https://thespacedevs-prod.nyc3.digitaloceanspaces.com/media/map_images/location_20_20200803142433.jpg",
            "timezone_name": "",
            "total_launch_count": 51,
            "total_landing_count": 0
        },
        "country_code": "USA",
        "map_image": "https://thespacedevs-prod.nyc3.digitaloceanspaces.com/media/map_images/pad_53_20200803143612.jpg",
        "total_launch_count": 5,
        "orbital_launch_attempt_count": 5
    },
    "webcast_live": false,
    "image": "https://thespacedevs-prod.nyc3.digitaloceanspaces.com/media/images/launcherone_image_20200101110016.jpeg",
    "infographic": "https://thespacedevs-prod.nyc3.digitaloceanspaces.com/media/infographic_images/launcherone252_infographic_20210114193003.png",
    "program": [],
    "orbital_launch_attempt_count": 6039,
    "location_launch_attempt_count": 46,
    "pad_launch_attempt_count": 2,
    "agency_launch_attempt_count": 2,
    "orbital_launch_attempt_count_year": 2,
    "location_launch_attempt_count_year": 1,
    "pad_launch_attempt_count_year": 1,
    "agency_launch_attempt_count_year": 1,
    "type": "normal"
}