{
    "id": "3f28ecb9-a83d-4424-882d-3710c686d69f",
    "url": "https://ll.thespacedevs.com/2.2.0/launch/3f28ecb9-a83d-4424-882d-3710c686d69f/",
    "slug": "long-march-2d-piesat-2-09-12",
    "name": "Long March 2D | PIESAT-2 09-12",
    "status": {
        "id": 3,
        "name": "Launch Successful",
        "abbrev": "Success",
        "description": "The launch vehicle successfully inserted its payload(s) into the target orbit(s)."
    },
    "last_updated": "2024-12-16T19:28:24Z",
    "net": "2024-12-16T18:50:00Z",
    "window_end": "2024-12-16T19:10:00Z",
    "window_start": "2024-12-16T18:42:00Z",
    "net_precision": {
        "id": 1,
        "name": "Minute",
        "abbrev": "MIN",
        "description": "The T-0 is accurate to the minute."
    },
    "probability": null,
    "weather_concerns": null,
    "holdreason": "",
    "failreason": "",
    "hashtag": null,
    "launch_service_provider": {
        "id": 88,
        "url": "https://ll.thespacedevs.com/2.2.0/agencies/88/",
        "name": "China Aerospace Science and Technology Corporation",
        "type": "Government"
    },
    "rocket": {
        "id": 8442,
        "configuration": {
            "id": 17,
            "url": "https://ll.thespacedevs.com/2.2.0/config/launcher/17/",
            "name": "Long March 2D",
            "family": "Long March",
            "full_name": "Long March 2D",
            "variant": "2D"
        }
    },
    "mission": {
        "id": 7031,
        "name": "PIESAT-2 09-12",
        "description": "4 X-band synthetic-aperture radar Earth observation satellites for the Chinese Earth observation satellite company PIESAT.",
        "launch_designator": null,
        "type": "Earth Science",
        "orbit": {
            "id": 17,
            "name": "Sun-Synchronous Orbit",
            "abbrev": "SSO"
        },
        "agencies": [],
        "info_urls": [],
        "vid_urls": []
    },
    "pad": {
        "id": 25,
        "url": "https://ll.thespacedevs.com/2.2.0/pad/25/",
        "agency_id": null,
        "name": "Launch Complex 9",
        "description": "",
        "info_url": null,
        "wiki_url": null,
        "map_url": "https://www.google.com/maps?q=38.863128,111.589567",
        "latitude": "38.863128",
        "longitude": "111.589567",
        "location": {
            "id": 19,
            "url": "https://ll.thespacedevs.com/2.2.0/location/19/",
            "name": "Taiyuan Satellite Launch Center, People's Republic of China",
            "country_code": "CHN",
            "description": "The Taiyuan Satellite Launch Center is a People's Republic of China space and defense launch facility. It is situated in Kelan County, Xinzhou, Shanxi Province and is the second of four launch sites having been founded in March 1966 and coming into full operation in 1968.",
            "map_image": "https://thespacedevs-prod.nyc3.digitaloceanspaces.com/media/map_images/location_19_20200803142421.jpg",
            "timezone_name": "Asia/Shanghai",
            "total_launch_count": 137,
            "total_landing_count": 0
        },
        "country_code": "CHN",
        "map_image": "https://thespacedevs-prod.nyc3.digitaloceanspaces.com/media/map_images/pad_25_20200803143501.jpg",
        "total_launch_count": 76,
        "orbital_launch_attempt_count": 76
    },
    "webcast_live": false,
    "image": "https://thespacedevs-prod.nyc3.digitaloceanspaces.com/media/images/long2520march25202d_image_20190222031211.jpeg",
    "infographic": null,
    "program": [],
    "orbital_launch_attempt_count": 6834,
    "location_launch_attempt_count": 137,
    "pad_launch_attempt_count": 76,
    "agency_launch_attempt_count": 500,
    "orbital_launch_attempt_count_year": 245,
    "location_launch_attempt_count_year": 13,
    "pad_launch_attempt_count_year": 5,
    "agency_launch_attempt_count_year": 48,
    "type": "normal"
}