{
    "id": "8ba623d1-294b-4734-b412-23fc6d202e5b",
    "url": "https://ll.thespacedevs.com/2.2.0/launch/8ba623d1-294b-4734-b412-23fc6d202e5b/",
    "slug": "proton-kdm-2m-astra-1g",
    "name": "Proton-K/DM-2M | Astra 1G",
    "status": {
        "id": 3,
        "name": "Launch Successful",
        "abbrev": "Success",
        "description": "The launch vehicle successfully inserted its payload(s) into the target orbit(s)."
    },
    "last_updated": "2023-06-14T03:46:16Z",
    "net": "1997-12-02T23:10:37Z",
    "window_end": "1997-12-02T23:10:37Z",
    "window_start": "1997-12-02T23:10:37Z",
    "net_precision": null,
    "probability": null,
    "weather_concerns": null,
    "holdreason": "",
    "failreason": null,
    "hashtag": null,
    "launch_service_provider": {
        "id": 96,
        "url": "https://ll.thespacedevs.com/2.2.0/agencies/96/",
        "name": "Khrunichev State Research and Production Space Center",
        "type": "Government"
    },
    "rocket": {
        "id": 6823,
        "configuration": {
            "id": 350,
            "url": "https://ll.thespacedevs.com/2.2.0/config/launcher/350/",
            "name": "Proton-K/DM-2M",
            "family": "Proton / UR-500",
            "full_name": "Proton-K/DM-2M",
            "variant": "DM-2M"
        }
    },
    "mission": {
        "id": 5213,
        "name": "Astra 1G",
        "description": "SES ordered its Hughes 601 satellites, in 1994 for Astra 1G; in 1995 for Astra 1H; and in 1996 for Astra 2A. In August 1999, SES ordered Astra 2C, another Hughes 601HP",
        "launch_designator": null,
        "type": "Communications",
        "orbit": {
            "id": 1,
            "name": "Geostationary Orbit",
            "abbrev": "Direct-GEO"
        },
        "agencies": [],
        "info_urls": [],
        "vid_urls": []
    },
    "pad": {
        "id": 31,
        "url": "https://ll.thespacedevs.com/2.2.0/pad/31/",
        "agency_id": null,
        "name": "81/23 (81L)",
        "description": null,
        "info_url": null,
        "wiki_url": "",
        "map_url": "https://www.google.com/maps?q=46.073997,62.977999",
        "latitude": "46.073997",
        "longitude": "62.977999",
        "location": {
            "id": 15,
            "url": "https://ll.thespacedevs.com/2.2.0/location/15/",
            "name": "Baikonur Cosmodrome, Republic of Kazakhstan",
            "country_code": "KAZ",
            "description": "The Baikonur Cosmodrome is a spaceport operated by Russia within Kazakhstan. Located in the Kazakh city of Baikonur, it is the largest operational space launch facility in terms of area. All Russian crewed spaceflights are launched from Baikonur.",
            "map_image": "https://thespacedevs-prod.nyc3.digitaloceanspaces.com/media/map_images/location_15_20200803142517.jpg",
            "timezone_name": "Asia/Qyzylorda",
            "total_launch_count": 1552,
            "total_landing_count": 0
        },
        "country_code": "KAZ",
        "map_image": "https://thespacedevs-prod.nyc3.digitaloceanspaces.com/media/map_images/pad_31_20200803143402.jpg",
        "total_launch_count": 104,
        "orbital_launch_attempt_count": 104
    },
    "webcast_live": false,
    "image": "https://thespacedevs-prod.nyc3.digitaloceanspaces.com/media/images/proton_image_20231231095535.jpg",
    "infographic": null,
    "program": [],
    "orbital_launch_attempt_count": 4197,
    "location_launch_attempt_count": 1099,
    "pad_launch_attempt_count": 76,
    "agency_launch_attempt_count": 50,
    "orbital_launch_attempt_count_year": 79,
    "location_launch_attempt_count_year": 15,
    "pad_launch_attempt_count_year": 5,
    "agency_launch_attempt_count_year": 8,
    "type": "normal"
}