{
    "id": "7bb575d4-0d47-41c6-8512-b1b0b7fd4580",
    "url": "https://ll.thespacedevs.com/2.2.0/launch/7bb575d4-0d47-41c6-8512-b1b0b7fd4580/",
    "slug": "atlas-v-401-tdrs-k",
    "name": "Atlas V 401 | TDRS-K",
    "status": {
        "id": 3,
        "name": "Launch Successful",
        "abbrev": "Success",
        "description": "The launch vehicle successfully inserted its payload(s) into the target orbit(s)."
    },
    "last_updated": "2023-06-14T17:42:25Z",
    "net": "2013-01-31T01:48:00Z",
    "window_end": "2013-01-31T01:48:00Z",
    "window_start": "2013-01-31T01:48:00Z",
    "net_precision": null,
    "probability": -1,
    "weather_concerns": null,
    "holdreason": "",
    "failreason": null,
    "hashtag": null,
    "launch_service_provider": {
        "id": 124,
        "url": "https://ll.thespacedevs.com/2.2.0/agencies/124/",
        "name": "United Launch Alliance",
        "type": "Commercial"
    },
    "rocket": {
        "id": 1658,
        "configuration": {
            "id": 16,
            "url": "https://ll.thespacedevs.com/2.2.0/config/launcher/16/",
            "name": "Atlas V 401",
            "family": "Atlas",
            "full_name": "Atlas V 401",
            "variant": "401"
        }
    },
    "mission": {
        "id": 20,
        "name": "TDRS-K",
        "description": "TDRS-11, known before launch as TDRS-K, is an American communications satellite which is operated by NASA as part of the Tracking and Data Relay Satellite System, which provides a multitude of communications services to a wide variety of missions.",
        "launch_designator": null,
        "type": "Communications",
        "orbit": {
            "id": 2,
            "name": "Geostationary Transfer Orbit",
            "abbrev": "GTO"
        },
        "agencies": [],
        "info_urls": [],
        "vid_urls": []
    },
    "pad": {
        "id": 29,
        "url": "https://ll.thespacedevs.com/2.2.0/pad/29/",
        "agency_id": null,
        "name": "Space Launch Complex 41",
        "description": "",
        "info_url": null,
        "wiki_url": "https://en.wikipedia.org/wiki/Cape_Canaveral_Air_Force_Station_Space_Launch_Complex_41",
        "map_url": "https://www.google.com/maps?q=28.58341025,-80.58303644",
        "latitude": "28.58341025",
        "longitude": "-80.58303644",
        "location": {
            "id": 12,
            "url": "https://ll.thespacedevs.com/2.2.0/location/12/",
            "name": "Cape Canaveral SFS, FL, USA",
            "country_code": "USA",
            "description": "Cape Canaveral Space Force Station (CCSFS) is an installation of the United States Space Force's Space Launch Delta 45, located on Cape Canaveral in Brevard County, Florida.",
            "map_image": "https://thespacedevs-prod.nyc3.digitaloceanspaces.com/media/map_images/location_12_20200803142519.jpg",
            "timezone_name": "America/New_York",
            "total_launch_count": 989,
            "total_landing_count": 59
        },
        "country_code": "USA",
        "map_image": "https://thespacedevs-prod.nyc3.digitaloceanspaces.com/media/map_images/pad_29_20200803143528.jpg",
        "total_launch_count": 114,
        "orbital_launch_attempt_count": 114
    },
    "webcast_live": false,
    "image": "https://thespacedevs-prod.nyc3.digitaloceanspaces.com/media/images/atlas_v_image_20201212013334.jpeg",
    "infographic": null,
    "program": [],
    "orbital_launch_attempt_count": 5272,
    "location_launch_attempt_count": 694,
    "pad_launch_attempt_count": 57,
    "agency_launch_attempt_count": 68,
    "orbital_launch_attempt_count_year": 4,
    "location_launch_attempt_count_year": 1,
    "pad_launch_attempt_count_year": 1,
    "agency_launch_attempt_count_year": 1,
    "type": "normal"
}