{
    "id": "e1c98771-b043-45e3-92a4-0925bef897f8",
    "url": "https://ll.thespacedevs.com/2.2.0/launch/e1c98771-b043-45e3-92a4-0925bef897f8/",
    "slug": "soyuz-u-soyuz-28",
    "name": "Soyuz-U | Soyuz 28",
    "status": {
        "id": 3,
        "name": "Launch Successful",
        "abbrev": "Success",
        "description": "The launch vehicle successfully inserted its payload(s) into the target orbit(s)."
    },
    "last_updated": "2024-06-15T14:08:16Z",
    "net": "1978-03-02T15:28:10Z",
    "window_end": "1978-03-02T15:28:10Z",
    "window_start": "1978-03-02T15:28:10Z",
    "net_precision": {
        "id": 0,
        "name": "Second",
        "abbrev": "SEC",
        "description": "The T-0 is accurate to the second."
    },
    "probability": null,
    "weather_concerns": null,
    "holdreason": "",
    "failreason": "",
    "hashtag": null,
    "launch_service_provider": {
        "id": 66,
        "url": "https://ll.thespacedevs.com/2.2.0/agencies/66/",
        "name": "Soviet Space Program",
        "type": "Government"
    },
    "rocket": {
        "id": 265,
        "configuration": {
            "id": 37,
            "url": "https://ll.thespacedevs.com/2.2.0/config/launcher/37/",
            "name": "Soyuz U",
            "family": "Soyuz",
            "full_name": "Soyuz U",
            "variant": ""
        }
    },
    "mission": {
        "id": 317,
        "name": "Soyuz 28",
        "description": "Soyuz 28 was the third mission to visit the Salyut 6 space station. This mission, being the first of the Intercosmos program, had the first ever international crew. The mission began on March 2, 1978, 15:28 UTC, launching Commander Aleksei Gubarev and Research Cosmonaut Vladim\u00c3\u00adr Remek into orbit. They docked with the station the next day and greeted the crew of the long0duration EO-1 expedition. During their stay on the station, Soyuz 28 crew performed various scientific and technological experiments. \nThe mission concluded with a safe landing back on Earth on March 10, 1978, 13:44 UTC.",
        "launch_designator": null,
        "type": "Human Exploration",
        "orbit": {
            "id": 8,
            "name": "Low Earth Orbit",
            "abbrev": "LEO"
        },
        "agencies": [],
        "info_urls": [],
        "vid_urls": []
    },
    "pad": {
        "id": 32,
        "url": "https://ll.thespacedevs.com/2.2.0/pad/32/",
        "agency_id": null,
        "name": "1/5",
        "description": null,
        "info_url": null,
        "wiki_url": "",
        "map_url": "https://www.google.com/maps?q=45.92,63.342",
        "latitude": "45.92",
        "longitude": "63.342",
        "location": {
            "id": 15,
            "url": "https://ll.thespacedevs.com/2.2.0/location/15/",
            "name": "Baikonur Cosmodrome, Republic of Kazakhstan",
            "country_code": "KAZ",
            "description": "The Baikonur Cosmodrome is a spaceport operated by Russia within Kazakhstan. Located in the Kazakh city of Baikonur, it is the largest operational space launch facility in terms of area. All Russian crewed spaceflights are launched from Baikonur.",
            "map_image": "https://thespacedevs-prod.nyc3.digitaloceanspaces.com/media/map_images/location_15_20200803142517.jpg",
            "timezone_name": "Asia/Qyzylorda",
            "total_launch_count": 1552,
            "total_landing_count": 0
        },
        "country_code": "KAZ",
        "map_image": "https://thespacedevs-prod.nyc3.digitaloceanspaces.com/media/map_images/pad_32_20200803143513.jpg",
        "total_launch_count": 487,
        "orbital_launch_attempt_count": 487
    },
    "webcast_live": false,
    "image": "https://thespacedevs-prod.nyc3.digitaloceanspaces.com/media/images/soyuz2520u_image_20190222031023.jpeg",
    "infographic": null,
    "program": [
        {
            "id": 8,
            "url": "https://ll.thespacedevs.com/2.2.0/program/8/",
            "name": "Soyuz",
            "description": "The Soyuz programme is a human spaceflight programme initiated by the Soviet Union in the early 1960s. The Soyuz spacecraft was originally part of a Moon landing project intended to put a Soviet cosmonaut on the Moon. It was the third Soviet human spaceflight programme after the Vostok and Voskhod programmes.",
            "agencies": [
                {
                    "id": 63,
                    "url": "https://ll.thespacedevs.com/2.2.0/agencies/63/",
                    "name": "Russian Federal Space Agency (ROSCOSMOS)",
                    "type": "Government"
                },
                {
                    "id": 66,
                    "url": "https://ll.thespacedevs.com/2.2.0/agencies/66/",
                    "name": "Soviet Space Program",
                    "type": "Government"
                }
            ],
            "image_url": "https://thespacedevs-prod.nyc3.digitaloceanspaces.com/media/images/soyuz_program_20201129185543.png",
            "start_date": "1966-11-28T11:02:00Z",
            "end_date": null,
            "info_url": null,
            "wiki_url": "https://en.wikipedia.org/wiki/Soyuz_programme",
            "mission_patches": [],
            "type": {
                "id": 2,
                "name": "Human Spaceflight"
            }
        },
        {
            "id": 23,
            "url": "https://ll.thespacedevs.com/2.2.0/program/23/",
            "name": "Salyut",
            "description": "The Salyut programme was the first space station programme, undertaken by the Soviet Union. It involved a series of four crewed scientific research space stations and two crewed military reconnaissance space stations over a period of 15 years, from 1971 to 1986.",
            "agencies": [
                {
                    "id": 66,
                    "url": "https://ll.thespacedevs.com/2.2.0/agencies/66/",
                    "name": "Soviet Space Program",
                    "type": "Government"
                }
            ],
            "image_url": "https://thespacedevs-prod.nyc3.digitaloceanspaces.com/media/images/salyut_program_20230506090532.png",
            "start_date": "1971-04-19T01:40:00Z",
            "end_date": "1986-07-16T12:34:05Z",
            "info_url": null,
            "wiki_url": "https://en.wikipedia.org/wiki/Salyut_programme",
            "mission_patches": [],
            "type": {
                "id": 2,
                "name": "Human Spaceflight"
            }
        }
    ],
    "orbital_launch_attempt_count": 2068,
    "location_launch_attempt_count": 512,
    "pad_launch_attempt_count": 164,
    "agency_launch_attempt_count": 1197,
    "orbital_launch_attempt_count_year": 23,
    "location_launch_attempt_count_year": 5,
    "pad_launch_attempt_count_year": 2,
    "agency_launch_attempt_count_year": 15,
    "type": "normal"
}